meds_torch_data-0.6.6.dist-info/licenses/LICENSE
meds_torchdata/__init__.py
meds_torchdata/config.py
meds_torchdata/pytest_plugin.py
meds_torchdata/pytorch_dataset.py
meds_torchdata/types.py
meds_torchdata/utils.py
meds_torchdata/extensions/__init__.py
meds_torchdata/extensions/lightning_datamodule.py
meds_torchdata/preprocessing/README.md
meds_torchdata/preprocessing/__init__.py
meds_torchdata/preprocessing/__main__.py
meds_torchdata/preprocessing/tensorization.py
meds_torchdata/preprocessing/tokenization.py
meds_torchdata/preprocessing/configs/_MTD_preprocess.yaml
meds_torchdata/preprocessing/configs/__init__.py
meds_torchdata/preprocessing/configs/_reshard_then_MTD_preprocess.yaml
meds_torchdata/preprocessing/configs/main.yaml
meds_torchdata/preprocessing/configs/runner.yaml
meds_torch_data-0.6.6.dist-info/METADATA
meds_torch_data-0.6.6.dist-info/WHEEL
meds_torch_data-0.6.6.dist-info/entry_points.txt
meds_torch_data-0.6.6.dist-info/top_level.txt
meds_torch_data-0.6.6.dist-info/RECORD
