Metadata-Version: 2.4
Name: meds-torch-data
Version: 0.6.6
Summary: An efficient, flexible PyTorch dataset class for MEDS data.
Author-email: Matthew McDermott <mattmcdermott8@gmail.com>, Nassim Oufattole <noufattole@gmail.com>, Teya Bergamaschi <teyabergamaschi@gmail.com>, Aleksia Kolo <aleksiakolo@gmail.com>
Project-URL: Homepage, https://github.com/mmcdermott/meds-torch-data
Project-URL: Issues, https://github.com/mmcdermott/meds-torch-data/issues
Classifier: Programming Language :: Python :: 3
Classifier: License :: OSI Approved :: MIT License
Classifier: Operating System :: OS Independent
Requires-Python: >=3.11
License-File: LICENSE
Requires-Dist: pytest
Requires-Dist: polars~=1.30.0
Requires-Dist: nested_ragged_tensors>=0.1.0
Requires-Dist: numpy
Requires-Dist: torch
Requires-Dist: meds~=0.4.0
Requires-Dist: MEDS_transforms~=0.5.2
Requires-Dist: hydra-core
Requires-Dist: omegaconf
Requires-Dist: meds_testing_helpers>=0.3.0
Provides-Extra: parallelized
Requires-Dist: hydra-joblib-launcher~=1.2.0; extra == "parallelized"
Provides-Extra: lightning
Requires-Dist: lightning~=2.5.1; extra == "lightning"
Dynamic: license-file
